pytest_pylint/__init__.py
pytest_pylint/plugin.py
pytest_pylint/pylint_util.py
pytest_pylint/util.py
pytest_pylint-0.21.0.dist-info/LICENSE
pytest_pylint-0.21.0.dist-info/METADATA
pytest_pylint-0.21.0.dist-info/WHEEL
pytest_pylint-0.21.0.dist-info/entry_points.txt
pytest_pylint-0.21.0.dist-info/top_level.txt
pytest_pylint-0.21.0.dist-info/RECORD
