Metadata-Version: 2.1
Name: pytest-pylint
Version: 0.21.0
Summary: pytest plugin to check source code with pylint
Home-page: https://github.com/carsongee/pytest-pylint
Author: Carson Gee
Author-email: x@carsongee.com
License: MIT
Classifier: Development Status :: 5 - Production/Stable
Classifier: Intended Audience :: Developers
Classifier: License :: OSI Approved :: MIT License
Classifier: Programming Language :: Python :: 3.8
Classifier: Programming Language :: Python :: 3.9
Classifier: Programming Language :: Python :: 3.10
Classifier: Programming Language :: Python :: 3.11
Classifier: Programming Language :: Python :: 3.12
Requires-Python: >=3.7
License-File: LICENSE
